{"560117":[{"office":"Devanagundi B.O","type":"BO","delivery":"Non Delivery","division":"Bengaluru East Division","region":"Bengaluru HQ Region","circle":"Karnataka Circle","taluk":"","district":"BENGALURU RURAL","state":"KARNATAKA","lat":"NA","lng":"NA"},{"office":"Samethanahalli B.O","type":"BO","delivery":"Non Delivery","division":"Bengaluru East Division","region":"Bengaluru HQ Region","circle":"Karnataka Circle","taluk":"","district":"BENGALURU RURAL","state":"KARNATAKA","lat":"NA","lng":"NA"},{"office":"Kalkunte B.O","type":"BO","delivery":"Non Delivery","division":"Bengaluru East Division","region":"Bengaluru HQ Region","circle":"Karnataka Circle","taluk":"","district":"BENGALURU RURAL","state":"KARNATAKA","lat":"NA","lng":"NA"},{"office":"ANUGONDANAHALLI B.O","type":"BO","delivery":"Non Delivery","division":"Bengaluru East Division","region":"Bengaluru HQ Region","circle":"Karnataka Circle","taluk":"","district":"BENGALURU RURAL","state":"KARNATAKA","lat":"NA","lng":"NA"},{"office":"Doddadunnasandra S.O","type":"PO","delivery":"Delivery","division":"Bengaluru East Division","region":"Bengaluru HQ Region","circle":"Karnataka Circle","taluk":"","district":"BENGALURU RURAL","state":"KARNATAKA","lat":"12.969569999999999","lng":"77.822433000000004"}],"560064":[{"office":"Singanayakanahalli B.O","type":"BO","delivery":"Non Delivery","division":"Bengaluru East Division","region":"Bengaluru HQ Region","circle":"Karnataka Circle","taluk":"","district":"BENGALURU URBAN","state":"KARNATAKA","lat":"13.148968","lng":"77.553343999999996"},{"office":"Jakkur B.O","type":"BO","delivery":"Non Delivery","division":"Bengaluru East Division","region":"Bengaluru HQ Region","circle":"Karnataka Circle","taluk":"","district":"BENGALURU URBAN","state":"KARNATAKA","lat":"13.063141","lng":"77.620677000000001"},{"office":"Rajanakunte B.O","type":"BO","delivery":"Non Delivery","division":"Bengaluru East Division","region":"Bengaluru HQ Region","circle":"Karnataka Circle","taluk":"","district":"BENGALURU URBAN","state":"KARNATAKA","lat":"13.187006999999999","lng":"77.550196"},{"office":"Yelahanka Satellite Town S.O","type":"PO","delivery":"Non Delivery","division":"Bengaluru East Division","region":"Bengaluru HQ Region","circle":"Karnataka Circle","taluk":"","district":"BENGALURU URBAN","state":"KARNATAKA","lat":"13.0852778","lng":"77.568805600000005"},{"office":"Yelahanka S.O","type":"PO","delivery":"Delivery","division":"Bengaluru East Division","region":"Bengaluru HQ Region","circle":"Karnataka Circle","taluk":"","district":"BENGALURU URBAN","state":"KARNATAKA","lat":"13.085777800000001","lng":"77.585611099999994"},{"office":"Attur B.O","type":"BO","delivery":"Non Delivery","division":"Bengaluru East Division","region":"Bengaluru HQ Region","circle":"Karnataka Circle","taluk":"","district":"BENGALURU URBAN","state":"KARNATAKA","lat":"13.106961999999999","lng":"77.566299000000001"}],"560077":[{"office":"Doddagubbi B.O","type":"BO","delivery":"Non Delivery","division":"Bengaluru East Division","region":"Bengaluru HQ Region","circle":"Karnataka Circle","taluk":"","district":"BENGALURU URBAN","state":"KARNATAKA","lat":"13.06362","lng":"77.648933999999997"},{"office":"Kannur B.O","type":"BO","delivery":"Non Delivery","division":"Bengaluru East Division","region":"Bengaluru HQ Region","circle":"Karnataka Circle","taluk":"","district":"BENGALURU URBAN","state":"KARNATAKA","lat":"13.09","lng":"77.659999999999997"},{"office":"Dr. Shivarama Karanth Nagar S.O","type":"PO","delivery":"Delivery","division":"Bengaluru East Division","region":"Bengaluru HQ Region","circle":"Karnataka Circle","taluk":"","district":"BENGALURU URBAN","state":"KARNATAKA","lat":"13.068138899999999","lng":"77.629222200000001"},{"office":"Kothanur S.O","type":"PO","delivery":"Non Delivery","division":"Bengaluru East Division","region":"Bengaluru HQ Region","circle":"Karnataka Circle","taluk":"","district":"BENGALURU URBAN","state":"KARNATAKA","lat":"13.063750000000001","lng":"77.648861100000005"}],"560116":[{"office":"Taralu B.O","type":"BO","delivery":"Delivery","division":"Bengaluru South Division","region":"Bengaluru HQ Region","circle":"Karnataka Circle","taluk":"","district":"BENGALURU URBAN","state":"KARNATAKA","lat":"12.790295800000001","lng":"77.520598699999994"},{"office":"Thattekuppe B.O","type":"BO","delivery":"Delivery","division":"Bengaluru South Division","region":"Bengaluru HQ Region","circle":"Karnataka Circle","taluk":"","district":"BENGALURU URBAN","state":"KARNATAKA","lat":"12.7716169","lng":"77.529546600000003"},{"office":"Kaggalipura P.O","type":"PO","delivery":"Delivery","division":"Bengaluru South Division","region":"Bengaluru HQ Region","circle":"Karnataka Circle","taluk":"","district":"BENGALURU URBAN","state":"KARNATAKA","lat":"12.8001342","lng":"77.508131800000001"},{"office":"Bolare B.O","type":"BO","delivery":"Delivery","division":"Bengaluru South Division","region":"Bengaluru HQ Region","circle":"Karnataka Circle","taluk":"","district":"BENGALURU URBAN","state":"KARNATAKA","lat":"12.7542791","lng":"77.484528400000002"},{"office":"Somanhalli B.O","type":"BO","delivery":"Delivery","division":"Bengaluru South Division","region":"Bengaluru HQ Region","circle":"Karnataka Circle","taluk":"","district":"BENGALURU URBAN","state":"KARNATAKA","lat":"12.772035300000001","lng":"77.503271600000005"}],"560073":[{"office":"Nelakadiranahalli B.O","type":"BO","delivery":"Non Delivery","division":"Bengaluru West Division","region":"Bengaluru HQ Region","circle":"Karnataka Circle","taluk":"","district":"BENGALURU URBAN","state":"KARNATAKA","lat":"13.4430930","lng":"77.6292700"},{"office":"Nagasandra S.O (Bengaluru)","type":"PO","delivery":"Delivery","division":"Bengaluru West Division","region":"Bengaluru HQ Region","circle":"Karnataka Circle","taluk":"","district":"BENGALURU URBAN","state":"KARNATAKA","lat":"13.056573","lng":"77.508083"},{"office":"Chikkabidarkal S.O","type":"PO","delivery":"Non Delivery","division":"Bengaluru West Division","region":"Bengaluru HQ Region","circle":"Karnataka Circle","taluk":"","district":"BENGALURU URBAN","state":"KARNATAKA","lat":"13.047907","lng":"77.486483000000007"},{"office":"BAGALGUNTE S.O","type":"PO","delivery":"Non Delivery","division":"Bengaluru West Division","region":"Bengaluru HQ Region","circle":"Karnataka Circle","taluk":"","district":"BENGALURU URBAN","state":"KARNATAKA","lat":"13.056573","lng":"77.508082999999999"}],"560091":[{"office":"Bapagrama B.O","type":"BO","delivery":"Delivery","division":"Bengaluru West Division","region":"Bengaluru HQ Region","circle":"Karnataka Circle","taluk":"","district":"BENGALURU URBAN","state":"KARNATAKA","lat":"12.9996610","lng":"77.4510370"},{"office":"Sir M.VISVESVARAYA NAGARA S.O","type":"PO","delivery":"Non Delivery","division":"Bengaluru West Division","region":"Bengaluru HQ Region","circle":"Karnataka Circle","taluk":"","district":"BENGALURU URBAN","state":"KARNATAKA","lat":"12.971569","lng":"77.492306"},{"office":"Herohalli S.O","type":"PO","delivery":"Non Delivery","division":"Bengaluru West Division","region":"Bengaluru HQ Region","circle":"Karnataka Circle","taluk":"","district":"BENGALURU URBAN","state":"KARNATAKA","lat":"12.990615","lng":"77.487875000000003"},{"office":"Viswaneedam S.O","type":"PO","delivery":"Delivery","division":"Bengaluru West Division","region":"Bengaluru HQ Region","circle":"Karnataka Circle","taluk":"","district":"BENGALURU URBAN","state":"KARNATAKA","lat":"12.9909900","lng":"77.5027310"}],"560037":[{"office":"Kundalahalli S.O","type":"PO","delivery":"Non Delivery","division":"Bengaluru East Division","region":"Bengaluru HQ Region","circle":"Karnataka Circle","taluk":"","district":"BENGALURU URBAN","state":"KARNATAKA","lat":"12.9588611","lng":"77.716027800000006"},{"office":"Marathahalli Colony S.O","type":"PO","delivery":"Delivery","division":"Bengaluru East Division","region":"Bengaluru HQ Region","circle":"Karnataka Circle","taluk":"","district":"BENGALURU URBAN","state":"KARNATAKA","lat":"12.995900000000001","lng":"77.688199999999995"},{"office":"Rameshnagar S.O","type":"PO","delivery":"Non Delivery","division":"Bengaluru East Division","region":"Bengaluru HQ Region","circle":"Karnataka Circle","taluk":"","district":"BENGALURU URBAN","state":"KARNATAKA","lat":"12.9642778","lng":"77.682444399999994"},{"office":"Doddanekkundi SO","type":"PO","delivery":"Non Delivery","division":"Bengaluru East Division","region":"Bengaluru HQ Region","circle":"Karnataka Circle","taluk":"","district":"BENGALURU URBAN","state":"KARNATAKA","lat":"12.972089","lng":"77.694363999999993"}],"560016":[{"office":"Ramamurthy Nagar S.O","type":"PO","delivery":"Non Delivery","division":"Bengaluru East Division","region":"Bengaluru HQ Region","circle":"Karnataka Circle","taluk":"","district":"BENGALURU URBAN","state":"KARNATAKA","lat":"13.014083299999999","lng":"77.682749999999999"},{"office":"Doorvaninagar S.O","type":"PO","delivery":"Delivery","division":"Bengaluru East Division","region":"Bengaluru HQ Region","circle":"Karnataka Circle","taluk":"","district":"BENGALURU URBAN","state":"KARNATAKA","lat":"13.0044722","lng":"77.683305599999997"},{"office":"Krishnarajapuram R S S.O","type":"PO","delivery":"Non Delivery","division":"Bengaluru East Division","region":"Bengaluru HQ Region","circle":"Karnataka Circle","taluk":"","district":"BENGALURU URBAN","state":"KARNATAKA","lat":"12.9853889","lng":"77.677138900000003"}],"560065":[{"office":"G K V K S.O","type":"PO","delivery":"Delivery","division":"Bengaluru East Division","region":"Bengaluru HQ Region","circle":"Karnataka Circle","taluk":"","district":"BENGALURU URBAN","state":"KARNATAKA","lat":"13.0685556","lng":"77.568805600000005"}],"560024":[{"office":"H A Farm S.O","type":"PO","delivery":"Delivery","division":"Bengaluru East Division","region":"Bengaluru HQ Region","circle":"Karnataka Circle","taluk":"","district":"BENGALURU URBAN","state":"KARNATAKA","lat":"13.030435000000001","lng":"77.586663999999999"},{"office":"Hebbal Kempapura S.O","type":"PO","delivery":"Non Delivery","division":"Bengaluru East Division","region":"Bengaluru HQ Region","circle":"Karnataka Circle","taluk":"","district":"BENGALURU URBAN","state":"KARNATAKA","lat":"13.0492778","lng":"77.604555599999998"},{"office":"Anandanagar S.O","type":"PO","delivery":"Non Delivery","division":"Bengaluru East Division","region":"Bengaluru HQ Region","circle":"Karnataka Circle","taluk":"","district":"BENGALURU URBAN","state":"KARNATAKA","lat":"13.033045","lng":"77.590663000000006"}],"560094":[{"office":"ISRO Anthariksha Bhavan S.O","type":"PO","delivery":"Non Delivery","division":"Bengaluru East Division","region":"Bengaluru HQ Region","circle":"Karnataka Circle","taluk":"","district":"BENGALURU URBAN","state":"KARNATAKA","lat":"12.035277799999999","lng":"77.571083299999998"},{"office":"R M V Extension II Stage S.O","type":"PO","delivery":"Delivery","division":"Bengaluru East Division","region":"Bengaluru HQ Region","circle":"Karnataka Circle","taluk":"","district":"BENGALURU URBAN","state":"KARNATAKA","lat":"13.038371","lng":"77.574731999999997"}],"560092":[{"office":"Sahakaranagar S.O","type":"PO","delivery":"Delivery","division":"Bengaluru East Division","region":"Bengaluru HQ Region","circle":"Karnataka Circle","taluk":"","district":"BENGALURU URBAN","state":"KARNATAKA","lat":"13.052055599999999","lng":"77.599083300000004"},{"office":"Kodigehalli B.O","type":"BO","delivery":"Non Delivery","division":"Bengaluru East Division","region":"Bengaluru HQ Region","circle":"Karnataka Circle","taluk":"","district":"BENGALURU URBAN","state":"KARNATAKA","lat":"12.975161999999999","lng":"77.467329000000007"},{"office":"Amruthahalli B.O","type":"BO","delivery":"Non Delivery","division":"Bengaluru East Division","region":"Bengaluru HQ Region","circle":"Karnataka Circle","taluk":"","district":"BENGALURU URBAN","state":"KARNATAKA","lat":"13.056891999999999","lng":"77.598543000000006"},{"office":"Byatarayanapura B.O","type":"BO","delivery":"Non Delivery","division":"Bengaluru East Division","region":"Bengaluru HQ Region","circle":"Karnataka Circle","taluk":"","district":"BENGALURU URBAN","state":"KARNATAKA","lat":"12.949788","lng":"77.541162"}],"560006":[{"office":"Training Command IAF S.O","type":"PO","delivery":"Non Delivery","division":"Bengaluru East Division","region":"Bengaluru HQ Region","circle":"Karnataka Circle","taluk":"","district":"BENGALURU URBAN","state":"KARNATAKA","lat":"13.0168333","lng":"77.583277800000005"},{"office":"Benson Town S.O","type":"PO","delivery":"Non Delivery","division":"Bengaluru East Division","region":"Bengaluru HQ Region","circle":"Karnataka Circle","taluk":"","district":"BENGALURU URBAN","state":"KARNATAKA","lat":"NA","lng":"NA"},{"office":"J C Nagar S.O","type":"PO","delivery":"Delivery","division":"Bengaluru East Division","region":"Bengaluru HQ Region","circle":"Karnataka Circle","taluk":"","district":"BENGALURU URBAN","state":"KARNATAKA","lat":"13.021641000000001","lng":"77.592752000000004"}],"560001":[{"office":"Dr. Ambedkar Veedhi S.O","type":"PO","delivery":"Non Delivery","division":"Bengaluru East Division","region":"Bengaluru HQ Region","circle":"Karnataka Circle","taluk":"","district":"BENGALURU URBAN","state":"KARNATAKA","lat":"12.981138899999999","lng":"77.595361100000005"},{"office":"Vidhana Soudha S.O","type":"PO","delivery":"Non Delivery","division":"Bengaluru East Division","region":"Bengaluru HQ Region","circle":"Karnataka Circle","taluk":"","district":"BENGALURU URBAN","state":"KARNATAKA","lat":"12.987472199999999","lng":"77.604749999999996"},{"office":"Vasanthanagar S.O","type":"PO","delivery":"Non Delivery","division":"Bengaluru East Division","region":"Bengaluru HQ Region","circle":"Karnataka Circle","taluk":"","district":"BENGALURU URBAN","state":"KARNATAKA","lat":"12.993510000000001","lng":"77.592101"},{"office":"CMM Court Complex S.O","type":"PO","delivery":"Non Delivery","division":"Bengaluru East Division","region":"Bengaluru HQ Region","circle":"Karnataka Circle","taluk":"","district":"BENGALURU URBAN","state":"KARNATAKA","lat":"12.97949","lng":"77.594183000000001"},{"office":"Bengaluru G.P.O.","type":"HO","delivery":"Delivery","division":"Bengaluru GPO Division","region":"Bengaluru HQ Region","circle":"Karnataka Circle","taluk":"","district":"BENGALURU URBAN","state":"KARNATAKA","lat":"12.9715990","lng":"77.5945630"},{"office":"HighCourt S.O","type":"PO","delivery":"Non Delivery","division":"Bengaluru East Division","region":"Bengaluru HQ Region","circle":"Karnataka Circle","taluk":"","district":"BENGALURU URBAN","state":"KARNATAKA","lat":"12.968416700000001","lng":"77.569194400000001"},{"office":"Legislators Home S.O","type":"PO","delivery":"Non Delivery","division":"Bengaluru East Division","region":"Bengaluru HQ Region","circle":"Karnataka Circle","taluk":"","district":"BENGALURU URBAN","state":"KARNATAKA","lat":"12.9838611","lng":"77.589611099999999"},{"office":"Mahatma Gandhi Road S.O","type":"PO","delivery":"Non Delivery","division":"Bengaluru East Division","region":"Bengaluru HQ Region","circle":"Karnataka Circle","taluk":"","district":"BENGALURU URBAN","state":"KARNATAKA","lat":"12.161027799999999","lng":"78.000222199999996"},{"office":"Rajbhavan S.O","type":"PO","delivery":"Non Delivery","division":"Bengaluru East Division","region":"Bengaluru HQ Region","circle":"Karnataka Circle","taluk":"","district":"BENGALURU URBAN","state":"KARNATAKA","lat":"12.982467","lng":"77.591302999999996"}],"560051":[{"office":"H K P Road S.O","type":"PO","delivery":"Delivery","division":"Bengaluru East Division","region":"Bengaluru HQ Region","circle":"Karnataka Circle","taluk":"","district":"BENGALURU URBAN","state":"KARNATAKA","lat":"12.1553889","lng":"78.011805600000002"}],"560025":[{"office":"Richmond Town S.O","type":"PO","delivery":"Non Delivery","division":"Bengaluru East Division","region":"Bengaluru HQ Region","circle":"Karnataka Circle","taluk":"","district":"BENGALURU URBAN","state":"KARNATAKA","lat":"12.16325","lng":"78.013416699999993"},{"office":"CMP Centre And School S.O","type":"PO","delivery":"Non Delivery","division":"Bengaluru East Division","region":"Bengaluru HQ Region","circle":"Karnataka Circle","taluk":"","district":"BENGALURU URBAN","state":"KARNATAKA","lat":"12.9548056","lng":"77.608638900000003"},{"office":"Museum Road S.O","type":"PO","delivery":"Delivery","division":"Bengaluru East Division","region":"Bengaluru HQ Region","circle":"Karnataka Circle","taluk":"","district":"BENGALURU URBAN","state":"KARNATAKA","lat":"12.9748333","lng":"77.603999999999999"}],"560030":[{"office":"Adugodi S.O","type":"PO","delivery":"Delivery","division":"Bengaluru South Division","region":"Bengaluru HQ Region","circle":"Karnataka Circle","taluk":"","district":"BENGALURU URBAN","state":"KARNATAKA","lat":"12.9485278","lng":"77.6017222"}],"560002":[{"office":"Bengaluru Corporation Building S.O","type":"PO","delivery":"Non Delivery","division":"Bengaluru South Division","region":"Bengaluru HQ Region","circle":"Karnataka Circle","taluk":"","district":"BENGALURU URBAN","state":"KARNATAKA","lat":"12.9651111","lng":"77.587611100000004"},{"office":"Bengaluru City S.O","type":"PO","delivery":"Delivery","division":"Bengaluru West Division","region":"Bengaluru HQ Region","circle":"Karnataka Circle","taluk":"","district":"BENGALURU URBAN","state":"KARNATAKA","lat":"12.839909","lng":"77.662968000000006"}],"560060":[{"office":"Kengeri S.O","type":"PO","delivery":"Delivery","division":"Bengaluru South Division","region":"Bengaluru HQ Region","circle":"Karnataka Circle","taluk":"","district":"BENGALURU URBAN","state":"KARNATAKA","lat":"12.915575199999999","lng":"77.481582299999999"},{"office":"Chudenapura B.O","type":"BO","delivery":"Delivery","division":"Bengaluru South Division","region":"Bengaluru HQ Region","circle":"Karnataka Circle","taluk":"","district":"BENGALURU URBAN","state":"KARNATAKA","lat":"12.899117199999999","lng":"77.487332899999998"},{"office":"Sulikere B.O","type":"BO","delivery":"Delivery","division":"Bengaluru South Division","region":"Bengaluru HQ Region","circle":"Karnataka Circle","taluk":"","district":"BENGALURU RURAL","state":"KARNATAKA","lat":"12.940326600000001","lng":"77.448119000000005"}],"560059":[{"office":"Rv Niketan S.O","type":"PO","delivery":"Delivery","division":"Bengaluru South Division","region":"Bengaluru HQ Region","circle":"Karnataka Circle","taluk":"","district":"BENGALURU URBAN","state":"KARNATAKA","lat":"12.924909299999999","lng":"77.499209800000003"}],"560034":[{"office":"St. Johns Medical College S.O","type":"PO","delivery":"Non Delivery","division":"Bengaluru South Division","region":"Bengaluru HQ Region","circle":"Karnataka Circle","taluk":"","district":"BENGALURU URBAN","state":"KARNATAKA","lat":"12.9296881","lng":"77.621498399999993"},{"office":"Koramangala S.O","type":"PO","delivery":"Delivery","division":"Bengaluru South Division","region":"Bengaluru HQ Region","circle":"Karnataka Circle","taluk":"","district":"BENGALURU URBAN","state":"KARNATAKA","lat":"12.9271111","lng":"77.6266050"},{"office":"Koramangala I Block S.O","type":"PO","delivery":"Non Delivery","division":"Bengaluru South Division","region":"Bengaluru HQ Region","circle":"Karnataka Circle","taluk":"","district":"BENGALURU URBAN","state":"KARNATAKA","lat":"12.921502","lng":"77.631808899999996"}],"560018":[{"office":"Goripalya SO","type":"PO","delivery":"Non Delivery","division":"Bengaluru South Division","region":"Bengaluru HQ Region","circle":"Karnataka Circle","taluk":"","district":"BENGALURU URBAN","state":"KARNATAKA","lat":"12.96481","lng":"77.555014999999997"},{"office":"Chamrajpet S.O (Bengaluru)","type":"PO","delivery":"Delivery","division":"Bengaluru South Division","region":"Bengaluru HQ Region","circle":"Karnataka Circle","taluk":"","district":"BENGALURU URBAN","state":"KARNATAKA","lat":"12.956166899999999","lng":"77.566105500000006"}],"560068":[{"office":"Bommanahalli S.O (Bengaluru)","type":"PO","delivery":"Delivery","division":"Bengaluru South Division","region":"Bengaluru HQ Region","circle":"Karnataka Circle","taluk":"","district":"BENGALURU URBAN","state":"KARNATAKA","lat":"12.9069859","lng":"77.630843299999995"},{"office":"Madivala S.O","type":"PO","delivery":"Non Delivery","division":"Bengaluru South Division","region":"Bengaluru HQ Region","circle":"Karnataka Circle","taluk":"","district":"BENGALURU URBAN","state":"KARNATAKA","lat":"12.9228217","lng":"77.617732599999997"},{"office":"Singasandra B.O","type":"BO","delivery":"Non Delivery","division":"Bengaluru South Division","region":"Bengaluru HQ Region","circle":"Karnataka Circle","taluk":"","district":"BENGALURU URBAN","state":"KARNATAKA","lat":"12.877546000000001","lng":"77.647633900000002"},{"office":"KUDLU S.O","type":"PO","delivery":"Non Delivery","division":"Bengaluru South Division","region":"Bengaluru HQ Region","circle":"Karnataka Circle","taluk":"","district":"BENGALURU URBAN","state":"KARNATAKA","lat":"12.8886891","lng":"77.657046"}],"560099":[{"office":"Bommasandra Industrial Estate S.O","type":"PO","delivery":"Delivery","division":"Bengaluru South Division","region":"Bengaluru HQ Region","circle":"Karnataka Circle","taluk":"","district":"BENGALURU URBAN","state":"KARNATAKA","lat":"12.8192992","lng":"77.688124500000001"},{"office":"Huskur B.O","type":"BO","delivery":"Delivery","division":"Bengaluru South Division","region":"Bengaluru HQ Region","circle":"Karnataka Circle","taluk":"","district":"BENGALURU URBAN","state":"KARNATAKA","lat":"12.860980700000001","lng":"77.706975099999994"}],"560062":[{"office":"Doddakallasandra S.O","type":"PO","delivery":"Delivery","division":"Bengaluru South Division","region":"Bengaluru HQ Region","circle":"Karnataka Circle","taluk":"","district":"BENGALURU URBAN","state":"KARNATAKA","lat":"12.887145","lng":"77.557870699999995"},{"office":"Konanakunte S.O","type":"PO","delivery":"Non Delivery","division":"Bengaluru South Division","region":"Bengaluru HQ Region","circle":"Karnataka Circle","taluk":"","district":"BENGALURU URBAN","state":"KARNATAKA","lat":"12.9269167","lng":"77.591777800000003"}],"560105":[{"office":"Jigani S.O","type":"PO","delivery":"Delivery","division":"Bengaluru South Division","region":"Bengaluru HQ Region","circle":"Karnataka Circle","taluk":"","district":"BENGALURU URBAN","state":"KARNATAKA","lat":"12.786833700000001","lng":"77.637752599999999"},{"office":"Haragadde B.O","type":"BO","delivery":"Delivery","division":"Bengaluru South Division","region":"Bengaluru HQ Region","circle":"Karnataka Circle","taluk":"","district":"BENGALURU URBAN","state":"KARNATAKA","lat":"12.7630693","lng":"77.656485200000006"},{"office":"Hulimangala B.O","type":"BO","delivery":"Delivery","division":"Bengaluru South Division","region":"Bengaluru HQ Region","circle":"Karnataka Circle","taluk":"","district":"BENGALURU URBAN","state":"KARNATAKA","lat":"12.81887","lng":"77.637892100000002"},{"office":"Kallubalu B.O","type":"BO","delivery":"Delivery","division":"Bengaluru South Division","region":"Bengaluru HQ Region","circle":"Karnataka Circle","taluk":"","district":"BENGALURU URBAN","state":"KARNATAKA","lat":"12.7704293","lng":"77.622517700000003"},{"office":"Hennagara B.O","type":"BO","delivery":"Delivery","division":"Bengaluru South Division","region":"Bengaluru HQ Region","circle":"Karnataka Circle","taluk":"","district":"BENGALURU URBAN","state":"KARNATAKA","lat":"12.7885718","lng":"77.672878800000007"}],"560070":[{"office":"Padmanabhnagar S.O","type":"PO","delivery":"Non Delivery","division":"Bengaluru South Division","region":"Bengaluru HQ Region","circle":"Karnataka Circle","taluk":"","district":"BENGALURU URBAN","state":"KARNATAKA","lat":"12.918605299999999","lng":"77.557575999999997"},{"office":"Thyagarajnagar S.O","type":"PO","delivery":"Non Delivery","division":"Bengaluru South Division","region":"Bengaluru HQ Region","circle":"Karnataka Circle","taluk":"","district":"BENGALURU URBAN","state":"KARNATAKA","lat":"12.9351384","lng":"77.568530199999998"},{"office":"B Sk II Stage S.O","type":"PO","delivery":"Delivery","division":"Bengaluru South Division","region":"Bengaluru HQ Region","circle":"Karnataka Circle","taluk":"","district":"BENGALURU URBAN","state":"KARNATAKA","lat":"12.9264159","lng":"77.569656699999996"}],"560098":[{"office":"Pattanagere P.O","type":"PO","delivery":"Non Delivery","division":"Bengaluru South Division","region":"Bengaluru HQ Region","circle":"Karnataka Circle","taluk":"","district":"BENGALURU URBAN","state":"KARNATAKA","lat":"12.920648999999999","lng":"77.510795999999999"},{"office":"Rajarajeshwarinagar S.O","type":"PO","delivery":"Delivery","division":"Bengaluru South Division","region":"Bengaluru HQ Region","circle":"Karnataka Circle","taluk":"","district":"BENGALURU URBAN","state":"KARNATAKA","lat":"12.914319900000001","lng":"77.520796200000007"},{"office":"Channasandra PO","type":"PO","delivery":"Non Delivery","division":"Bengaluru South Division","region":"Bengaluru HQ Region","circle":"Karnataka Circle","taluk":"","district":"BENGALURU URBAN","state":"KARNATAKA","lat":"12.903983","lng":"77.514600999999999"},{"office":"Rajarajeshwarinagar Parcel Processing Center","type":"PO","delivery":"Non Delivery","division":"Bengaluru South Division","region":"Bengaluru HQ Region","circle":"Karnataka Circle","taluk":"","district":"NA","state":"NA","lat":"12.914","lng":"77.52"}],"560088":[{"office":"Hessarghatta S.O","type":"PO","delivery":"Delivery","division":"Bengaluru West Division","region":"Bengaluru HQ Region","circle":"Karnataka Circle","taluk":"","district":"BENGALURU URBAN","state":"KARNATAKA","lat":"13.133998999999999","lng":"77.478801000000004"}],"560058":[{"office":"Laggere S.O","type":"PO","delivery":"Non Delivery","division":"Bengaluru West Division","region":"Bengaluru HQ Region","circle":"Karnataka Circle","taluk":"","district":"BENGALURU URBAN","state":"KARNATAKA","lat":"13.010654000000001","lng":"77.523283000000006"},{"office":"Peenya Small Industries S.O","type":"PO","delivery":"Delivery","division":"Bengaluru West Division","region":"Bengaluru HQ Region","circle":"Karnataka Circle","taluk":"","district":"BENGALURU URBAN","state":"KARNATAKA","lat":"13.016539","lng":"77.507576999999998"},{"office":"Peenya I Stage S.O","type":"PO","delivery":"Non Delivery","division":"Bengaluru West Division","region":"Bengaluru HQ Region","circle":"Karnataka Circle","taluk":"","district":"BENGALURU URBAN","state":"KARNATAKA","lat":"13.034557","lng":"77.526201"}],"560054":[{"office":"Msrit S.O","type":"PO","delivery":"Delivery","division":"Bengaluru West Division","region":"Bengaluru HQ Region","circle":"Karnataka Circle","taluk":"","district":"BENGALURU URBAN","state":"KARNATAKA","lat":"13.029819","lng":"77.563733999999997"},{"office":"Sri Chowdeshwari S.O","type":"PO","delivery":"Non Delivery","division":"Bengaluru West Division","region":"Bengaluru HQ Region","circle":"Karnataka Circle","taluk":"","district":"BENGALURU URBAN","state":"KARNATAKA","lat":"13.034865999999999","lng":"77.553383999999994"},{"office":"Mathikere S.O","type":"PO","delivery":"Non Delivery","division":"Bengaluru West Division","region":"Bengaluru HQ Region","circle":"Karnataka Circle","taluk":"","district":"BENGALURU URBAN","state":"KARNATAKA","lat":"13.028746","lng":"77.557982999999993"}],"560022":[{"office":"Yeswanthpura S.O","type":"PO","delivery":"Delivery","division":"Bengaluru West Division","region":"Bengaluru HQ Region","circle":"Karnataka Circle","taluk":"","district":"BENGALURU URBAN","state":"KARNATAKA","lat":"13.027965999999999","lng":"77.540915999999996"},{"office":"Yeshwanthpur Bazar S.O","type":"PO","delivery":"Non Delivery","division":"Bengaluru West Division","region":"Bengaluru HQ Region","circle":"Karnataka Circle","taluk":"","district":"BENGALURU URBAN","state":"KARNATAKA","lat":"13.020059","lng":"77.556354999999996"}],"560010":[{"office":"Industrial Estate S.O (Bengaluru)","type":"PO","delivery":"Non Delivery","division":"Bengaluru West Division","region":"Bengaluru HQ Region","circle":"Karnataka Circle","taluk":"","district":"BENGALURU URBAN","state":"KARNATAKA","lat":"12.977667","lng":"77.549487999999997"},{"office":"Rajajinagar H.O","type":"HO","delivery":"Delivery","division":"Bengaluru West Division","region":"Bengaluru HQ Region","circle":"Karnataka Circle","taluk":"","district":"BENGALURU URBAN","state":"KARNATAKA","lat":"12.993209","lng":"77.554461000000003"},{"office":"Rajajinagar IVth Block S.O","type":"PO","delivery":"Non Delivery","division":"Bengaluru West Division","region":"Bengaluru HQ Region","circle":"Karnataka Circle","taluk":"","district":"BENGALURU URBAN","state":"KARNATAKA","lat":"12.983036999999999","lng":"77.560979000000003"}],"560079":[{"office":"Kamakshipalya S.O","type":"PO","delivery":"Non Delivery","division":"Bengaluru West Division","region":"Bengaluru HQ Region","circle":"Karnataka Circle","taluk":"","district":"BENGALURU URBAN","state":"KARNATAKA","lat":"12.987462000000001","lng":"77.528282000000004"},{"office":"Basaveshwaranagar S.O","type":"PO","delivery":"Delivery","division":"Bengaluru West Division","region":"Bengaluru HQ Region","circle":"Karnataka Circle","taluk":"","district":"BENGALURU URBAN","state":"KARNATAKA","lat":"12.993702000000001","lng":"77.539096999999998"},{"office":"K H B Colony S.O","type":"PO","delivery":"Non Delivery","division":"Bengaluru West Division","region":"Bengaluru HQ Region","circle":"Karnataka Circle","taluk":"","district":"BENGALURU URBAN","state":"KARNATAKA","lat":"12.982047","lng":"77.533118000000002"}],"560055":[{"office":"Malleswaram West S.O","type":"PO","delivery":"Delivery","division":"Bengaluru West Division","region":"Bengaluru HQ Region","circle":"Karnataka Circle","taluk":"","district":"BENGALURU URBAN","state":"KARNATAKA","lat":"13.009048999999999","lng":"77.562866999999997"}],"560072":[{"office":"Nagarbhavi S.O","type":"PO","delivery":"Delivery","division":"Bengaluru West Division","region":"Bengaluru HQ Region","circle":"Karnataka Circle","taluk":"","district":"BENGALURU URBAN","state":"KARNATAKA","lat":"12.955171999999999","lng":"77.515642999999997"},{"office":"Nagarbhavi II Stage PO","type":"PO","delivery":"Non Delivery","division":"Bengaluru West Division","region":"Bengaluru HQ Region","circle":"Karnataka Circle","taluk":"","district":"BENGALURU URBAN","state":"KARNATAKA","lat":"NA","lng":"NA"}],"560003":[{"office":"Swimming Pool Extn S.O","type":"PO","delivery":"Non Delivery","division":"Bengaluru West Division","region":"Bengaluru HQ Region","circle":"Karnataka Circle","taluk":"","district":"BENGALURU URBAN","state":"KARNATAKA","lat":"13.00273","lng":"77.571959000000007"},{"office":"Palace Guttahalli S.O","type":"PO","delivery":"Non Delivery","division":"Bengaluru West Division","region":"Bengaluru HQ Region","circle":"Karnataka Circle","taluk":"","district":"BENGALURU URBAN","state":"KARNATAKA","lat":"13.001938000000001","lng":"77.579071999999996"},{"office":"Malleswaram S.O","type":"PO","delivery":"Delivery","division":"Bengaluru West Division","region":"Bengaluru HQ Region","circle":"Karnataka Circle","taluk":"","district":"BENGALURU URBAN","state":"KARNATAKA","lat":"13.000127000000001","lng":"77.570627000000002"},{"office":"Vyalikaval Extn S.O","type":"PO","delivery":"Non Delivery","division":"Bengaluru West Division","region":"Bengaluru HQ Region","circle":"Karnataka Circle","taluk":"","district":"BENGALURU URBAN","state":"KARNATAKA","lat":"13.004047999999999","lng":"77.575562000000005"}],"560004":[{"office":"Basavanagudi H.O","type":"HO","delivery":"Delivery","division":"Bengaluru South Division","region":"Bengaluru HQ Region","circle":"Karnataka Circle","taluk":"","district":"BENGALURU URBAN","state":"KARNATAKA","lat":"12.9454166","lng":"77.573476200000002"},{"office":"Gaviopuram Extension S.O","type":"PO","delivery":"Non Delivery","division":"Bengaluru South Division","region":"Bengaluru HQ Region","circle":"Karnataka Circle","taluk":"","district":"BENGALURU URBAN","state":"KARNATAKA","lat":"12.9435713","lng":"77.565858700000007"},{"office":"Pampamahakavi Road S.O","type":"PO","delivery":"Non Delivery","division":"Bengaluru South Division","region":"Bengaluru HQ Region","circle":"Karnataka Circle","taluk":"","district":"BENGALURU URBAN","state":"KARNATAKA","lat":"12.9537529","lng":"77.572210200000001"},{"office":"Mavalli S.O","type":"PO","delivery":"Non Delivery","division":"Bengaluru South Division","region":"Bengaluru HQ Region","circle":"Karnataka Circle","taluk":"","district":"BENGALURU URBAN","state":"KARNATAKA","lat":"12.951403300000001","lng":"77.581554999999994"}],"560083":[{"office":"Sakalavara B.O","type":"BO","delivery":"Delivery","division":"Bengaluru South Division","region":"Bengaluru HQ Region","circle":"Karnataka Circle","taluk":"","district":"BENGALURU URBAN","state":"KARNATAKA","lat":"12.820608099999999","lng":"77.608977899999999"},{"office":"Bannerghatta S.O","type":"PO","delivery":"Delivery","division":"Bengaluru South Division","region":"Bengaluru HQ Region","circle":"Karnataka Circle","taluk":"","district":"BENGALURU URBAN","state":"KARNATAKA","lat":"12.812700899999999","lng":"77.581276000000003"},{"office":"Kalkere B.O","type":"BO","delivery":"Delivery","division":"Bengaluru South Division","region":"Bengaluru HQ Region","circle":"Karnataka Circle","taluk":"","district":"BENGALURU URBAN","state":"KARNATAKA","lat":"12.8309292","lng":"77.5880674"},{"office":"Ragihalli B.O","type":"BO","delivery":"Delivery","division":"Bengaluru South Division","region":"Bengaluru HQ Region","circle":"Karnataka Circle","taluk":"","district":"BENGALURU URBAN","state":"KARNATAKA","lat":"12.738543200000001","lng":"77.574527599999996"},{"office":"Gottigere S.O","type":"PO","delivery":"Non Delivery","division":"Bengaluru South Division","region":"Bengaluru HQ Region","circle":"Karnataka Circle","taluk":"","district":"BENGALURU URBAN","state":"KARNATAKA","lat":"12.8564531","lng":"77.5884322"}],"560089":[{"office":"Shivakote B.O","type":"BO","delivery":"Delivery","division":"Bengaluru West Division","region":"Bengaluru HQ Region","circle":"Karnataka Circle","taluk":"","district":"BENGALURU URBAN","state":"KARNATAKA","lat":"13.1335240","lng":"77.4911320"},{"office":"Kakolu B.O","type":"BO","delivery":"Delivery","division":"Bengaluru West Division","region":"Bengaluru HQ Region","circle":"Karnataka Circle","taluk":"","district":"BENGALURU URBAN","state":"KARNATAKA","lat":"13.1335240","lng":"77.4911320"},{"office":"Byatha B.O","type":"BO","delivery":"Delivery","division":"Bengaluru West Division","region":"Bengaluru HQ Region","circle":"Karnataka Circle","taluk":"","district":"BENGALURU URBAN","state":"KARNATAKA","lat":"13.1335240","lng":"77.4911320"},{"office":"Hessarghatta Lake S.O","type":"PO","delivery":"Delivery","division":"Bengaluru West Division","region":"Bengaluru HQ Region","circle":"Karnataka Circle","taluk":"","district":"BENGALURU URBAN","state":"KARNATAKA","lat":"13.1335240","lng":"77.4911320"}],"560066":[{"office":"E P I P S.O","type":"PO","delivery":"Non Delivery","division":"Bengaluru East Division","region":"Bengaluru HQ Region","circle":"Karnataka Circle","taluk":"","district":"BENGALURU URBAN","state":"KARNATAKA","lat":"12.987244","lng":"77.732161000000005"},{"office":"Whitefield S.O","type":"PO","delivery":"Delivery","division":"Bengaluru East Division","region":"Bengaluru HQ Region","circle":"Karnataka Circle","taluk":"","district":"BENGALURU URBAN","state":"KARNATAKA","lat":"12.967713","lng":"77.749442799999997"}],"560075":[{"office":"Jeevanbhimanagar S.O","type":"PO","delivery":"Non Delivery","division":"Bengaluru East Division","region":"Bengaluru HQ Region","circle":"Karnataka Circle","taluk":"","district":"BENGALURU URBAN","state":"KARNATAKA","lat":"12.9710833","lng":"77.656000000000006"},{"office":"New Thippasandra S.O","type":"PO","delivery":"Delivery","division":"Bengaluru East Division","region":"Bengaluru HQ Region","circle":"Karnataka Circle","taluk":"","district":"BENGALURU URBAN","state":"KARNATAKA","lat":"12.1560556","lng":"77.1145278"}],"560017":[{"office":"N A L S.O","type":"PO","delivery":"Non Delivery","division":"Bengaluru East Division","region":"Bengaluru HQ Region","circle":"Karnataka Circle","taluk":"","district":"BENGALURU URBAN","state":"KARNATAKA","lat":"12.166638900000001","lng":"77.113944399999994"},{"office":"Vimanapura S.O","type":"PO","delivery":"Delivery","division":"Bengaluru East Division","region":"Bengaluru HQ Region","circle":"Karnataka Circle","taluk":"","district":"BENGALURU URBAN","state":"KARNATAKA","lat":"12.944722199999999","lng":"77.574027799999996"}],"560047":[{"office":"Viveknagar S.O (Bengaluru)","type":"PO","delivery":"Delivery","division":"Bengaluru East Division","region":"Bengaluru HQ Region","circle":"Karnataka Circle","taluk":"","district":"BENGALURU URBAN","state":"KARNATAKA","lat":"12.944722199999999","lng":"77.574027799999996"},{"office":"Austin Town S.O","type":"PO","delivery":"Non Delivery","division":"Bengaluru East Division","region":"Bengaluru HQ Region","circle":"Karnataka Circle","taluk":"","district":"BENGALURU URBAN","state":"KARNATAKA","lat":"12.955416700000001","lng":"77.615694399999995"}],"560080":[{"office":"Sadashivanagar S.O","type":"PO","delivery":"Delivery","division":"Bengaluru East Division","region":"Bengaluru HQ Region","circle":"Karnataka Circle","taluk":"","district":"BENGALURU URBAN","state":"KARNATAKA","lat":"13.009323","lng":"77.576740999999998"}],"560119":[{"office":"Singanayakanahalli S.O","type":"PO","delivery":"Delivery","division":"Bengaluru East Division","region":"Bengaluru HQ Region","circle":"Karnataka Circle","taluk":"","district":"BENGALURU URBAN","state":"KARNATAKA","lat":"13.1483446","lng":"77.5674982"}],"560084":[{"office":"Lingarajapuram S.O","type":"PO","delivery":"Non Delivery","division":"Bengaluru East Division","region":"Bengaluru HQ Region","circle":"Karnataka Circle","taluk":"","district":"BENGALURU URBAN","state":"KARNATAKA","lat":"13.010472200000001","lng":"77.624694399999996"},{"office":"St. Thomas Town S.O","type":"PO","delivery":"Delivery","division":"Bengaluru East Division","region":"Bengaluru HQ Region","circle":"Karnataka Circle","taluk":"","district":"BENGALURU URBAN","state":"KARNATAKA","lat":"13.013388900000001","lng":"77.629750000000001"}],"560026":[{"office":"NAYANDAHALLI","type":"PO","delivery":"Non Delivery","division":"Bengaluru South Division","region":"Bengaluru HQ Region","circle":"Karnataka Circle","taluk":"","district":"BENGALURU URBAN","state":"KARNATAKA","lat":"12.949414000000001","lng":"77.536331500000003"},{"office":"Governmemnt Electric Factory S.O","type":"PO","delivery":"Delivery","division":"Bengaluru South Division","region":"Bengaluru HQ Region","circle":"Karnataka Circle","taluk":"","district":"BENGALURU URBAN","state":"KARNATAKA","lat":"12.9544029","lng":"77.544281600000005"}],"560074":[{"office":"Kumbalagodu S.O","type":"PO","delivery":"Delivery","division":"Bengaluru South Division","region":"Bengaluru HQ Region","circle":"Karnataka Circle","taluk":"","district":"BENGALURU URBAN","state":"KARNATAKA","lat":"12.879751600000001","lng":"77.446574100000007"},{"office":"Kumbalgodu Gollahalli B.O","type":"BO","delivery":"Delivery","division":"Bengaluru South Division","region":"Bengaluru HQ Region","circle":"Karnataka Circle","taluk":"","district":"BENGALURU URBAN","state":"KARNATAKA","lat":"12.8428337","lng":"77.451391299999997"},{"office":"Ramohalli B.O","type":"BO","delivery":"Delivery","division":"Bengaluru South Division","region":"Bengaluru HQ Region","circle":"Karnataka Circle","taluk":"","district":"BENGALURU URBAN","state":"KARNATAKA","lat":"12.9058978","lng":"77.418486000000001"}],"560110":[{"office":"Ullalu Upanagar S.O","type":"PO","delivery":"Delivery","division":"Bengaluru South Division","region":"Bengaluru HQ Region","circle":"Karnataka Circle","taluk":"","district":"BENGALURU URBAN","state":"KARNATAKA","lat":"12.958211","lng":"77.475639999999999"}],"560050":[{"office":"Ashoknagar S.O (Bengaluru)","type":"PO","delivery":"Non Delivery","division":"Bengaluru South Division","region":"Bengaluru HQ Region","circle":"Karnataka Circle","taluk":"","district":"BENGALURU URBAN","state":"KARNATAKA","lat":"12.9375901","lng":"77.564664100000002"},{"office":"Banashankari S.O","type":"PO","delivery":"Delivery","division":"Bengaluru South Division","region":"Bengaluru HQ Region","circle":"Karnataka Circle","taluk":"","district":"BENGALURU URBAN","state":"KARNATAKA","lat":"12.9421944","lng":"77.558083300000007"},{"office":"State Bank Of Mysuru Colony S.O","type":"PO","delivery":"Non Delivery","division":"Bengaluru South Division","region":"Bengaluru HQ Region","circle":"Karnataka Circle","taluk":"","district":"BENGALURU URBAN","state":"KARNATAKA","lat":"12.9379279","lng":"77.550956400000004"},{"office":"Dasarahalli(Srinagar) S.O","type":"PO","delivery":"Non Delivery","division":"Bengaluru South Division","region":"Bengaluru HQ Region","circle":"Karnataka Circle","taluk":"","district":"BENGALURU URBAN","state":"KARNATAKA","lat":"12.9445154","lng":"77.555848699999999"}],"560100":[{"office":"Electronics City S.O","type":"PO","delivery":"Delivery","division":"Bengaluru South Division","region":"Bengaluru HQ Region","circle":"Karnataka Circle","taluk":"","district":"BENGALURU URBAN","state":"KARNATAKA","lat":"12.8400702","lng":"77.663544799999997"}],"560076":[{"office":"Mico Layout S.O","type":"PO","delivery":"Non Delivery","division":"Bengaluru South Division","region":"Bengaluru HQ Region","circle":"Karnataka Circle","taluk":"","district":"BENGALURU URBAN","state":"KARNATAKA","lat":"12.9104513","lng":"77.6101259"},{"office":"Bannerghatta Road S.O","type":"PO","delivery":"Delivery","division":"Bengaluru South Division","region":"Bengaluru HQ Region","circle":"Karnataka Circle","taluk":"","district":"BENGALURU URBAN","state":"KARNATAKA","lat":"12.898649600000001","lng":"77.601027799999997"},{"office":"Mount St Joseph B.O","type":"BO","delivery":"Non Delivery","division":"Bengaluru South Division","region":"Bengaluru HQ Region","circle":"Karnataka Circle","taluk":"","district":"BENGALURU URBAN","state":"KARNATAKA","lat":"12.873233000000001","lng":"77.597068899999996"},{"office":"JP Nagar VIII phase S.O","type":"PO","delivery":"Non Delivery","division":"Bengaluru South Division","region":"Bengaluru HQ Region","circle":"Karnataka Circle","taluk":"","district":"BENGALURU URBAN","state":"KARNATAKA","lat":"12.8834865","lng":"77.583094200000005"}],"560029":[{"office":"Tavarekere S.O","type":"PO","delivery":"Non Delivery","division":"Bengaluru South Division","region":"Bengaluru HQ Region","circle":"Karnataka Circle","taluk":"","district":"BENGALURU URBAN","state":"KARNATAKA","lat":"12.922048999999999","lng":"77.610264999999998"},{"office":"Dharmaram College S.O","type":"PO","delivery":"Delivery","division":"Bengaluru South Division","region":"Bengaluru HQ Region","circle":"Karnataka Circle","taluk":"","district":"BENGALURU URBAN","state":"KARNATAKA","lat":"12.9376382","lng":"77.599139600000001"}],"560109":[{"office":"Thalaghattapura S.O","type":"PO","delivery":"Delivery","division":"Bengaluru South Division","region":"Bengaluru HQ Region","circle":"Karnataka Circle","taluk":"","district":"BENGALURU URBAN","state":"KARNATAKA","lat":"12.8684125","lng":"77.538118900000001"}],"560041":[{"office":"Jayanagar East S.O","type":"PO","delivery":"Non Delivery","division":"Bengaluru South Division","region":"Bengaluru HQ Region","circle":"Karnataka Circle","taluk":"","district":"BENGALURU URBAN","state":"KARNATAKA","lat":"12.919764000000001","lng":"77.592444799999996"},{"office":"Jayanagar H.O","type":"HO","delivery":"Delivery","division":"Bengaluru South Division","region":"Bengaluru HQ Region","circle":"Karnataka Circle","taluk":"","district":"BENGALURU URBAN","state":"KARNATAKA","lat":"12.9235083","lng":"77.585900199999998"},{"office":"Tilaknagar S.O (Bengaluru)","type":"PO","delivery":"Non Delivery","division":"Bengaluru South Division","region":"Bengaluru HQ Region","circle":"Karnataka Circle","taluk":"","district":"BENGALURU URBAN","state":"KARNATAKA","lat":"12.925729199999999","lng":"77.591704500000006"}],"560013":[{"office":"Jalahalli East S.O","type":"PO","delivery":"Non Delivery","division":"Bengaluru West Division","region":"Bengaluru HQ Region","circle":"Karnataka Circle","taluk":"","district":"BENGALURU URBAN","state":"KARNATAKA","lat":"13.064257","lng":"77.546487999999997"},{"office":"Jalahalli H.O","type":"HO","delivery":"Delivery","division":"Bengaluru West Division","region":"Bengaluru HQ Region","circle":"Karnataka Circle","taluk":"","district":"BENGALURU URBAN","state":"KARNATAKA","lat":"13.051064","lng":"77.552897000000002"}],"560009":[{"office":"Bengaluru Dist Offices Bldg S.O","type":"PO","delivery":"Non Delivery","division":"Bengaluru West Division","region":"Bengaluru HQ Region","circle":"Karnataka Circle","taluk":"","district":"BENGALURU URBAN","state":"KARNATAKA","lat":"12.972861999999999","lng":"77.583298999999997"},{"office":"K. G. Road S.O","type":"PO","delivery":"Delivery","division":"Bengaluru West Division","region":"Bengaluru HQ Region","circle":"Karnataka Circle","taluk":"","district":"BENGALURU URBAN","state":"KARNATAKA","lat":"12.973544","lng":"77.580324000000005"}],"560104":[{"office":"Hampinagar S.O","type":"PO","delivery":"Delivery","division":"Bengaluru West Division","region":"Bengaluru HQ Region","circle":"Karnataka Circle","taluk":"","district":"BENGALURU URBAN","state":"KARNATAKA","lat":"12.964979","lng":"77.538072"}],"560096":[{"office":"Nandinilayout S.O","type":"PO","delivery":"Delivery","division":"Bengaluru West Division","region":"Bengaluru HQ Region","circle":"Karnataka Circle","taluk":"","district":"BENGALURU URBAN","state":"KARNATAKA","lat":"13.011426","lng":"77.535876999999999"}],"560086":[{"office":"West of Chord Road II stage S.O","type":"PO","delivery":"Non Delivery","division":"Bengaluru West Division","region":"Bengaluru HQ Region","circle":"Karnataka Circle","taluk":"","district":"BENGALURU URBAN","state":"KARNATAKA","lat":"13.002878000000001","lng":"77.546368999999999"},{"office":"Mahalakshmipuram Layout S.O","type":"PO","delivery":"Delivery","division":"Bengaluru West Division","region":"Bengaluru HQ Region","circle":"Karnataka Circle","taluk":"","district":"BENGALURU URBAN","state":"KARNATAKA","lat":"13.010635000000001","lng":"77.546496000000005"}],"560112":[{"office":"Kodigehalli S.O","type":"PO","delivery":"Delivery","division":"Bengaluru West Division","region":"Bengaluru HQ Region","circle":"Karnataka Circle","taluk":"","district":"BENGALURU URBAN","state":"KARNATAKA","lat":"13.267671999999999","lng":"77.552379999999999"}],"560008":[{"office":"H A L II Stage H.O","type":"HO","delivery":"Delivery","division":"Bengaluru East Division","region":"Bengaluru HQ Region","circle":"Karnataka Circle","taluk":"","district":"BENGALURU URBAN","state":"KARNATAKA","lat":"12.968488000000001","lng":"77.642573999999996"},{"office":"Cambridge Layout S.O","type":"PO","delivery":"Non Delivery","division":"Bengaluru East Division","region":"Bengaluru HQ Region","circle":"Karnataka Circle","taluk":"","district":"BENGALURU URBAN","state":"KARNATAKA","lat":"12.1655833","lng":"77.106777800000003"}],"560032":[{"office":"R T Nagar H.O","type":"HO","delivery":"Delivery","division":"Bengaluru East Division","region":"Bengaluru HQ Region","circle":"Karnataka Circle","taluk":"","district":"BENGALURU URBAN","state":"KARNATAKA","lat":"13.021645299999999","lng":"77.592799799999995"},{"office":"P and T Colony Kavalbyrasandra S.O","type":"PO","delivery":"Non Delivery","division":"Bengaluru East Division","region":"Bengaluru HQ Region","circle":"Karnataka Circle","taluk":"","district":"BENGALURU URBAN","state":"KARNATAKA","lat":"13.022581000000001","lng":"77.593103999999997"}],"560067":[{"office":"Naduvathi B.O","type":"BO","delivery":"Non Delivery","division":"Bengaluru East Division","region":"Bengaluru HQ Region","circle":"Karnataka Circle","taluk":"","district":"BENGALURU RURAL","state":"KARNATAKA","lat":"12.9794","lng":"77.791499999999999"},{"office":"Kadugodi S.O","type":"PO","delivery":"Delivery","division":"Bengaluru East Division","region":"Bengaluru HQ Region","circle":"Karnataka Circle","taluk":"","district":"BENGALURU URBAN","state":"KARNATAKA","lat":"12.1518333","lng":"77.133444400000002"}],"560049":[{"office":"Mandur B.O","type":"BO","delivery":"Non Delivery","division":"Bengaluru East Division","region":"Bengaluru HQ Region","circle":"Karnataka Circle","taluk":"","district":"BENGALURU RURAL","state":"KARNATAKA","lat":"13.082573999999999","lng":"77.738460000000003"},{"office":"Bhattarahalli S.O","type":"PO","delivery":"Non Delivery","division":"Bengaluru East Division","region":"Bengaluru HQ Region","circle":"Karnataka Circle","taluk":"","district":"BENGALURU URBAN","state":"KARNATAKA","lat":"13.0188056","lng":"77.709916699999994"},{"office":"Bidrahalli B.O","type":"BO","delivery":"Non Delivery","division":"Bengaluru East Division","region":"Bengaluru HQ Region","circle":"Karnataka Circle","taluk":"","district":"BENGALURU URBAN","state":"KARNATAKA","lat":"13.061360000000001","lng":"77.715877000000006"},{"office":"Virgonagar S.O","type":"PO","delivery":"Delivery","division":"Bengaluru East Division","region":"Bengaluru HQ Region","circle":"Karnataka Circle","taluk":"","district":"BENGALURU RURAL","state":"KARNATAKA","lat":"13.0184167","lng":"77.718416700000006"}],"560090":[{"office":"Silvepura B.O","type":"BO","delivery":"Delivery","division":"Bengaluru West Division","region":"Bengaluru HQ Region","circle":"Karnataka Circle","taluk":"","district":"BENGALURU URBAN","state":"KARNATAKA","lat":"13.0862950","lng":"77.4973110"},{"office":"Chikkabanavara S.O","type":"PO","delivery":"Delivery","division":"Bengaluru West Division","region":"Bengaluru HQ Region","circle":"Karnataka Circle","taluk":"","district":"BENGALURU URBAN","state":"KARNATAKA","lat":"13.0862950","lng":"77.4973110"}],"560007":[{"office":"Agram S.O","type":"PO","delivery":"Delivery","division":"Bengaluru East Division","region":"Bengaluru HQ Region","circle":"Karnataka Circle","taluk":"","district":"BENGALURU URBAN","state":"KARNATAKA","lat":"12.16680556","lng":"77.106555560000004"},{"office":"Air Force Hospital S.O","type":"PO","delivery":"Non Delivery","division":"Bengaluru East Division","region":"Bengaluru HQ Region","circle":"Karnataka Circle","taluk":"","district":"BENGALURU URBAN","state":"KARNATAKA","lat":"12.963638899999999","lng":"77.629111100000003"}],"560036":[{"office":"Devasandra S.O","type":"PO","delivery":"Non Delivery","division":"Bengaluru East Division","region":"Bengaluru HQ Region","circle":"Karnataka Circle","taluk":"","district":"BENGALURU URBAN","state":"KARNATAKA","lat":"13.01075","lng":"77.685972199999995"},{"office":"Krishnarajapuram S.O","type":"PO","delivery":"Delivery","division":"Bengaluru East Division","region":"Bengaluru HQ Region","circle":"Karnataka Circle","taluk":"","district":"BENGALURU URBAN","state":"KARNATAKA","lat":"13.0051667","lng":"77.695999999999998"}],"560115":[{"office":"Kannamangala S.O","type":"PO","delivery":"Delivery","division":"Bengaluru East Division","region":"Bengaluru HQ Region","circle":"Karnataka Circle","taluk":"","district":"BENGALURU URBAN","state":"KARNATAKA","lat":"13.0469264","lng":"77.545425499999993"}],"560300":[{"office":"Kempegowda International Airport S.O","type":"PO","delivery":"Delivery","division":"Bengaluru East Division","region":"Bengaluru HQ Region","circle":"Karnataka Circle","taluk":"","district":"BENGALURU URBAN","state":"KARNATAKA","lat":"13.1989444","lng":"77.703999999999994"}],"560045":[{"office":"Arabic College S.O","type":"PO","delivery":"Delivery","division":"Bengaluru East Division","region":"Bengaluru HQ Region","circle":"Karnataka Circle","taluk":"","district":"BENGALURU URBAN","state":"KARNATAKA","lat":"13.032583300000001","lng":"77.620805599999997"}],"560043":[{"office":"Banaswadi S.O","type":"PO","delivery":"Non Delivery","division":"Bengaluru East Division","region":"Bengaluru HQ Region","circle":"Karnataka Circle","taluk":"","district":"BENGALURU URBAN","state":"KARNATAKA","lat":"13.0137778","lng":"77.652388900000005"},{"office":"Kalyananagar S.O","type":"PO","delivery":"Delivery","division":"Bengaluru East Division","region":"Bengaluru HQ Region","circle":"Karnataka Circle","taluk":"","district":"BENGALURU URBAN","state":"KARNATAKA","lat":"12.944722199999999","lng":"77.574027799999996"},{"office":"Jalavayuvihar S.O","type":"PO","delivery":"Non Delivery","division":"Bengaluru East Division","region":"Bengaluru HQ Region","circle":"Karnataka Circle","taluk":"","district":"BENGALURU URBAN","state":"KARNATAKA","lat":"13.0220278","lng":"77.634833299999997"}],"560005":[{"office":"Fraser Town S.O","type":"PO","delivery":"Delivery","division":"Bengaluru East Division","region":"Bengaluru HQ Region","circle":"Karnataka Circle","taluk":"","district":"BENGALURU URBAN","state":"KARNATAKA","lat":"13.0007222","lng":"77.616138899999996"}],"560053":[{"office":"Chickpet S.O","type":"PO","delivery":"Delivery","division":"Bengaluru South Division","region":"Bengaluru HQ Region","circle":"Karnataka Circle","taluk":"","district":"BENGALURU URBAN","state":"KARNATAKA","lat":"12.968891299999999","lng":"77.573089899999999"}],"560102":[{"office":"HSR Layout S.O","type":"PO","delivery":"Delivery","division":"Bengaluru South Division","region":"Bengaluru HQ Region","circle":"Karnataka Circle","taluk":"","district":"BENGALURU URBAN","state":"KARNATAKA","lat":"12.9141099","lng":"77.637151799999998"}],"560027":[{"office":"Sampangiramnagar S.O","type":"PO","delivery":"Non Delivery","division":"Bengaluru South Division","region":"Bengaluru HQ Region","circle":"Karnataka Circle","taluk":"","district":"BENGALURU URBAN","state":"KARNATAKA","lat":"12.967679","lng":"77.592219499999999"},{"office":"Shanthinagar S.O","type":"PO","delivery":"Non Delivery","division":"Bengaluru South Division","region":"Bengaluru HQ Region","circle":"Karnataka Circle","taluk":"","district":"BENGALURU URBAN","state":"KARNATAKA","lat":"12.961692299999999","lng":"77.597723299999998"},{"office":"Wilson Garden S.O","type":"PO","delivery":"Delivery","division":"Bengaluru South Division","region":"Bengaluru HQ Region","circle":"Karnataka Circle","taluk":"","district":"BENGALURU URBAN","state":"KARNATAKA","lat":"12.9486782","lng":"77.597766300000004"}],"560078":[{"office":"JP Nagar III Phase S.O","type":"PO","delivery":"Non Delivery","division":"Bengaluru South Division","region":"Bengaluru HQ Region","circle":"Karnataka Circle","taluk":"","district":"BENGALURU URBAN","state":"KARNATAKA","lat":"12.913991899999999","lng":"77.597669699999997"},{"office":"J P Nagar S.O","type":"PO","delivery":"Delivery","division":"Bengaluru South Division","region":"Bengaluru HQ Region","circle":"Karnataka Circle","taluk":"","district":"BENGALURU URBAN","state":"KARNATAKA","lat":"12.911942700000001","lng":"77.586865799999998"},{"office":"Yelachenahalli S.O","type":"PO","delivery":"Non Delivery","division":"Bengaluru South Division","region":"Bengaluru HQ Region","circle":"Karnataka Circle","taluk":"","district":"BENGALURU URBAN","state":"KARNATAKA","lat":"12.900194600000001","lng":"77.570858299999998"}],"560011":[{"office":"Madhavan Park S.O","type":"PO","delivery":"Non Delivery","division":"Bengaluru South Division","region":"Bengaluru HQ Region","circle":"Karnataka Circle","taluk":"","district":"BENGALURU URBAN","state":"KARNATAKA","lat":"12.936704799999999","lng":"77.585588999999999"},{"office":"Jayangar III Block S.O","type":"PO","delivery":"Delivery","division":"Bengaluru South Division","region":"Bengaluru HQ Region","circle":"Karnataka Circle","taluk":"","district":"BENGALURU URBAN","state":"KARNATAKA","lat":"12.9305035","lng":"77.583539799999997"}],"560107":[{"office":"Achitnagar S.O","type":"PO","delivery":"Delivery","division":"Bengaluru West Division","region":"Bengaluru HQ Region","circle":"Karnataka Circle","taluk":"","district":"BENGALURU URBAN","state":"KARNATAKA","lat":"13.089359999999999","lng":"77.485857999999993"}],"560015":[{"office":"Jalahalli West S.O","type":"PO","delivery":"Delivery","division":"Bengaluru West Division","region":"Bengaluru HQ Region","circle":"Karnataka Circle","taluk":"","district":"BENGALURU URBAN","state":"KARNATAKA","lat":"13.046435000000001","lng":"77.522696999999994"}],"560012":[{"office":"Science Institute S.O","type":"PO","delivery":"Delivery","division":"Bengaluru West Division","region":"Bengaluru HQ Region","circle":"Karnataka Circle","taluk":"","district":"BENGALURU URBAN","state":"KARNATAKA","lat":"13.01383","lng":"77.566540000000003"}],"560021":[{"office":"Gayathrinagar S.O","type":"PO","delivery":"Non Delivery","division":"Bengaluru West Division","region":"Bengaluru HQ Region","circle":"Karnataka Circle","taluk":"","district":"BENGALURU URBAN","state":"KARNATAKA","lat":"13.006429000000001","lng":"77.554956000000004"},{"office":"Srirampuram S.O","type":"PO","delivery":"Delivery","division":"Bengaluru West Division","region":"Bengaluru HQ Region","circle":"Karnataka Circle","taluk":"","district":"BENGALURU URBAN","state":"KARNATAKA","lat":"12.995151999999999","lng":"77.563756999999995"}],"560056":[{"office":"Mallathahalli B.O","type":"BO","delivery":"Non Delivery","division":"Bengaluru South Division","region":"Bengaluru HQ Region","circle":"Karnataka Circle","taluk":"","district":"BENGALURU URBAN","state":"KARNATAKA","lat":"12.959638","lng":"77.499606700000001"},{"office":"Bengaluru vishwavidyalaya S.O","type":"PO","delivery":"Delivery","division":"Bengaluru South Division","region":"Bengaluru HQ Region","circle":"Karnataka Circle","taluk":"","district":"BENGALURU URBAN","state":"KARNATAKA","lat":"12.950004","lng":"77.501741800000005"}],"560071":[{"office":"Domlur S.O","type":"PO","delivery":"Delivery","division":"Bengaluru East Division","region":"Bengaluru HQ Region","circle":"Karnataka Circle","taluk":"","district":"BENGALURU URBAN","state":"KARNATAKA","lat":"12.1669167","lng":"77.109972200000001"}],"560063":[{"office":"BSF Campus Yelahanka S.O","type":"PO","delivery":"Non Delivery","division":"Bengaluru East Division","region":"Bengaluru HQ Region","circle":"Karnataka Circle","taluk":"","district":"BENGALURU URBAN","state":"KARNATAKA","lat":"13.128","lng":"77.6076944"},{"office":"A F Station Yelahanka S.O","type":"PO","delivery":"Delivery","division":"Bengaluru East Division","region":"Bengaluru HQ Region","circle":"Karnataka Circle","taluk":"","district":"BENGALURU URBAN","state":"KARNATAKA","lat":"13.2187778","lng":"78.009027799999998"}],"560113":[{"office":"Horamavu S.O","type":"PO","delivery":"Delivery","division":"Bengaluru East Division","region":"Bengaluru HQ Region","circle":"Karnataka Circle","taluk":"","district":"BENGALURU URBAN","state":"KARNATAKA","lat":"13.025073000000001","lng":"77.659665000000004"}],"560035":[{"office":"Carmelram S.O","type":"PO","delivery":"Delivery","division":"Bengaluru South Division","region":"Bengaluru HQ Region","circle":"Karnataka Circle","taluk":"","district":"BENGALURU URBAN","state":"KARNATAKA","lat":"12.907511599999999","lng":"77.695677599999996"}],"560095":[{"office":"Koramangala VI Bk S.O","type":"PO","delivery":"Delivery","division":"Bengaluru South Division","region":"Bengaluru HQ Region","circle":"Karnataka Circle","taluk":"","district":"BENGALURU URBAN","state":"KARNATAKA","lat":"12.938453600000001","lng":"77.619148800000005"}],"560108":[{"office":"Anjanapura S.O","type":"PO","delivery":"Delivery","division":"Bengaluru South Division","region":"Bengaluru HQ Region","circle":"Karnataka Circle","taluk":"","district":"BENGALURU URBAN","state":"KARNATAKA","lat":"12.862436499999999","lng":"77.564425999999997"}],"560111":[{"office":"Kumaraswamy Layout S.O","type":"PO","delivery":"Delivery","division":"Bengaluru South Division","region":"Bengaluru HQ Region","circle":"Karnataka Circle","taluk":"","district":"BENGALURU URBAN","state":"KARNATAKA","lat":"12.896310700000001","lng":"77.559239000000005"}],"560082":[{"office":"Udaypura S.O","type":"PO","delivery":"Delivery","division":"Bengaluru South Division","region":"Bengaluru HQ Region","circle":"Karnataka Circle","taluk":"","district":"BENGALURU URBAN","state":"KARNATAKA","lat":"12.823297699999999","lng":"77.514064899999994"},{"office":"Thataguni B.O","type":"BO","delivery":"Delivery","division":"Bengaluru South Division","region":"Bengaluru HQ Region","circle":"Karnataka Circle","taluk":"","district":"BENGALURU URBAN","state":"KARNATAKA","lat":"12.843768300000001","lng":"77.509236900000005"}],"560114":[{"office":"Begur","type":"PO","delivery":"Delivery","division":"Bengaluru South Division","region":"Bengaluru HQ Region","circle":"Karnataka Circle","taluk":"","district":"BENGALURU URBAN","state":"KARNATAKA","lat":"12.870464999999999","lng":"77.626905800000003"}],"560081":[{"office":"Chandapura S.O","type":"PO","delivery":"Delivery","division":"Bengaluru South Division","region":"Bengaluru HQ Region","circle":"Karnataka Circle","taluk":"","district":"BENGALURU URBAN","state":"KARNATAKA","lat":"12.801736","lng":"77.704250000000002"}],"560097":[{"office":"Vidyaranyapura S.O","type":"PO","delivery":"Delivery","division":"Bengaluru West Division","region":"Bengaluru HQ Region","circle":"Karnataka Circle","taluk":"","district":"BENGALURU URBAN","state":"KARNATAKA","lat":"13.079368000000001","lng":"77.559539000000001"}],"560040":[{"office":"Chandra Lay Out S.O","type":"PO","delivery":"Non Delivery","division":"Bengaluru West Division","region":"Bengaluru HQ Region","circle":"Karnataka Circle","taluk":"","district":"BENGALURU URBAN","state":"KARNATAKA","lat":"12.958313","lng":"77.528676000000004"},{"office":"Vijayanagar East S.O","type":"PO","delivery":"Non Delivery","division":"Bengaluru West Division","region":"Bengaluru HQ Region","circle":"Karnataka Circle","taluk":"","district":"BENGALURU URBAN","state":"KARNATAKA","lat":"12.972659999999999","lng":"77.545649999999995"},{"office":"Vijayanagar S.O (Bengaluru)","type":"PO","delivery":"Delivery","division":"Bengaluru West Division","region":"Bengaluru HQ Region","circle":"Karnataka Circle","taluk":"","district":"BENGALURU URBAN","state":"KARNATAKA","lat":"12.971385","lng":"77.536849000000004"}],"560020":[{"office":"Seshadripuram S.O","type":"PO","delivery":"Delivery","division":"Bengaluru West Division","region":"Bengaluru HQ Region","circle":"Karnataka Circle","taluk":"","district":"BENGALURU URBAN","state":"KARNATAKA","lat":"12.988455999999999","lng":"77.574646999999999"}],"560048":[{"office":"Hoodi B.O","type":"BO","delivery":"Non Delivery","division":"Bengaluru East Division","region":"Bengaluru HQ Region","circle":"Karnataka Circle","taluk":"","district":"BENGALURU URBAN","state":"KARNATAKA","lat":"12.992214000000001","lng":"77.715900000000005"},{"office":"Mahadevapura S.O","type":"PO","delivery":"Delivery","division":"Bengaluru East Division","region":"Bengaluru HQ Region","circle":"Karnataka Circle","taluk":"","district":"BENGALURU URBAN","state":"KARNATAKA","lat":"12.9954444","lng":"77.699083299999998"}],"560087":[{"office":"Muthsandra B.O","type":"BO","delivery":"Non Delivery","division":"Bengaluru East Division","region":"Bengaluru HQ Region","circle":"Karnataka Circle","taluk":"","district":"BENGALURU RURAL","state":"KARNATAKA","lat":"12.977","lng":"77.567999999999998"},{"office":"Vartur S.O","type":"PO","delivery":"Delivery","division":"Bengaluru East Division","region":"Bengaluru HQ Region","circle":"Karnataka Circle","taluk":"","district":"BENGALURU URBAN","state":"KARNATAKA","lat":"12.9413333","lng":"77.746555599999994"},{"office":"Gunjur S.O","type":"PO","delivery":"Non Delivery","division":"Bengaluru East Division","region":"Bengaluru HQ Region","circle":"Karnataka Circle","taluk":"","district":"BENGALURU URBAN","state":"KARNATAKA","lat":"NA","lng":"NA"},{"office":"Panathur S.O","type":"PO","delivery":"Non Delivery","division":"Bengaluru East Division","region":"Bengaluru HQ Region","circle":"Karnataka Circle","taluk":"","district":"BENGALURU URBAN","state":"KARNATAKA","lat":"NA","lng":"NA"}],"560103":[{"office":"Bellandur S.O","type":"PO","delivery":"Delivery","division":"Bengaluru East Division","region":"Bengaluru HQ Region","circle":"Karnataka Circle","taluk":"","district":"BENGALURU URBAN","state":"KARNATAKA","lat":"12.935600000000001","lng":"77.705699999999993"}],"560093":[{"office":"C V Raman Nagar S.O","type":"PO","delivery":"Delivery","division":"Bengaluru East Division","region":"Bengaluru HQ Region","circle":"Karnataka Circle","taluk":"","district":"BENGALURU URBAN","state":"KARNATAKA","lat":"12.9861389","lng":"77.652166699999995"}],"560038":[{"office":"Indiranagar S.O (Bengaluru)","type":"PO","delivery":"Delivery","division":"Bengaluru East Division","region":"Bengaluru HQ Region","circle":"Karnataka Circle","taluk":"","district":"BENGALURU URBAN","state":"KARNATAKA","lat":"12.944722199999999","lng":"77.574027799999996"}],"560033":[{"office":"Maruthi Sevanagar S.O","type":"PO","delivery":"Delivery","division":"Bengaluru East Division","region":"Bengaluru HQ Region","circle":"Karnataka Circle","taluk":"","district":"BENGALURU URBAN","state":"KARNATAKA","lat":"13.0079444","lng":"77.109833300000005"}],"560042":[{"office":"Sivan Chetty Gardens S.O","type":"PO","delivery":"Delivery","division":"Bengaluru East Division","region":"Bengaluru HQ Region","circle":"Karnataka Circle","taluk":"","district":"BENGALURU URBAN","state":"KARNATAKA","lat":"12.982047","lng":"77.612380000000002"}],"560085":[{"office":"Banashankari III Stage S.O","type":"PO","delivery":"Delivery","division":"Bengaluru South Division","region":"Bengaluru HQ Region","circle":"Karnataka Circle","taluk":"","district":"BENGALURU URBAN","state":"KARNATAKA","lat":"12.9319519","lng":"77.541890499999994"},{"office":"Girinagar S.O (Bengaluru)","type":"PO","delivery":"Non Delivery","division":"Bengaluru South Division","region":"Bengaluru HQ Region","circle":"Karnataka Circle","taluk":"","district":"BENGALURU URBAN","state":"KARNATAKA","lat":"12.943281600000001","lng":"77.542555699999994"},{"office":"Kathriguppe S.O","type":"PO","delivery":"Non Delivery","division":"Bengaluru South Division","region":"Bengaluru HQ Region","circle":"Karnataka Circle","taluk":"","district":"BENGALURU URBAN","state":"KARNATAKA","lat":"12.9283363","lng":"77.550913399999999"}],"560061":[{"office":"Chikkalasandra S.O","type":"PO","delivery":"Non Delivery","division":"Bengaluru South Division","region":"Bengaluru HQ Region","circle":"Karnataka Circle","taluk":"","district":"BENGALURU URBAN","state":"KARNATAKA","lat":"12.9089031","lng":"77.549180300000003"},{"office":"Subramanyapura S.O","type":"PO","delivery":"Delivery","division":"Bengaluru South Division","region":"Bengaluru HQ Region","circle":"Karnataka Circle","taluk":"","district":"BENGALURU URBAN","state":"KARNATAKA","lat":"12.899086199999999","lng":"77.544148500000006"}],"560500":[{"office":"CPC ITD BNPL booking HUB","type":"PO","delivery":"Delivery","division":"Bengaluru South Division","region":"Bengaluru HQ Region","circle":"Karnataka Circle","taluk":"","district":"BENGALURU URBAN","state":"KARNATAKA","lat":"12.863319600000001","lng":"77.658309099999997"}],"560057":[{"office":"Peenya Dasarahalli S.O","type":"PO","delivery":"Delivery","division":"Bengaluru West Division","region":"Bengaluru HQ Region","circle":"Karnataka Circle","taluk":"","district":"BENGALURU URBAN","state":"KARNATAKA","lat":"13.046493999999999","lng":"77.512775000000005"}],"560023":[{"office":"Magadi Road S.O","type":"PO","delivery":"Delivery","division":"Bengaluru West Division","region":"Bengaluru HQ Region","circle":"Karnataka Circle","taluk":"","district":"BENGALURU URBAN","state":"KARNATAKA","lat":"12.975571","lng":"77.560338000000002"}]}